{"_type":"export","__export_format":4,"__export_date":"2022-06-11T23:50:41.878Z","__export_source":"insomnia.desktop.app:v2022.4.0","resources":[{"_id":"req_9ad264154c934b50b2e53ce7280b4c00","parentId":"fld_75cdec97598a45019c856e7064d8acad","modified":1654991241552,"created":1653858654308,"url":"{{ _.serverUrl }}:{{ _.serverPort }}/dev/author/generate","name":"generate","description":"","method":"POST","body":{"mimeType":"application/json","text":"{\n\t\"number\": 5\n}"},"parameters":[],"headers":[{"name":"Content-Type","value":"application/json","id":"pair_ecaf36ef21c747a9a920cc3500e7df71"}],"authentication":{"type":"bearer","token":"{% response 'body', 'req_ae2a859001a9428ea82d8e044d2d3eb1', 'b64::JC5hY2Nlc3NfdG9rZW4=::46b', 'always', 60 %}"},"metaSortKey":-1646673036429,"isPrivate":false,"settingStoreCookies":true,"settingSendCookies":true,"settingDisableRenderRequestBody":false,"settingEncodeUrl":true,"settingRebuildPath":true,"settingFollowRedirects":"global","_type":"request"},{"_id":"fld_75cdec97598a45019c856e7064d8acad","parentId":"fld_8fa0da45da9343238df5705e0b798b18","modified":1654991152850,"created":1653858044236,"name":"Author","description":"","environment":{},"environmentPropertyOrder":null,"metaSortKey":-1654990664360,"_type":"request_group"},{"_id":"fld_8fa0da45da9343238df5705e0b798b18","parentId":"wrk_d5720fa7dd8b432da33f10272aca5071","modified":1653831975818,"created":1653831975818,"name":"dev","description":"","environment":{},"environmentPropertyOrder":null,"metaSortKey":-1653831975818,"_type":"request_group"},{"_id":"wrk_d5720fa7dd8b432da33f10272aca5071","parentId":null,"modified":1646488846134,"created":1646488846134,"name":"Beta","description":"","scope":"collection","_type":"workspace"},{"_id":"req_8424260b799a46ddb2f807fb372923db","parentId":"fld_75cdec97598a45019c856e7064d8acad","modified":1654991203237,"created":1654991188782,"url":"{{ _.serverUrl }}:{{ _.serverPort }}/dev/author/mock-one","name":"mock-one","description":"","method":"POST","body":{"mimeType":"application/json","text":"{}"},"parameters":[],"headers":[{"name":"Content-Type","value":"application/json","id":"pair_ecaf36ef21c747a9a920cc3500e7df71"}],"authentication":{"type":"bearer","token":"{% response 'body', 'req_ae2a859001a9428ea82d8e044d2d3eb1', 'b64::JC5hY2Nlc3NfdG9rZW4=::46b', 'always', 60 %}"},"metaSortKey":-1646673036427.4375,"isPrivate":false,"settingStoreCookies":true,"settingSendCookies":true,"settingDisableRenderRequestBody":false,"settingEncodeUrl":true,"settingRebuildPath":true,"settingFollowRedirects":"global","_type":"request"},{"_id":"req_0d7506a0c2f64f0fa084b63d69285ea2","parentId":"fld_e535fc869e1d46c6804962e8fa266144","modified":1654991233796,"created":1654991222490,"url":"{{ _.serverUrl }}:{{ _.serverPort }}/dev/category/generate","name":"generate","description":"","method":"POST","body":{"mimeType":"application/json","text":"{\n\t\"number\": 5\n}"},"parameters":[],"headers":[{"name":"Content-Type","value":"application/json","id":"pair_ecaf36ef21c747a9a920cc3500e7df71"}],"authentication":{"type":"bearer","token":"{% response 'body', 'req_ae2a859001a9428ea82d8e044d2d3eb1', 'b64::JC5hY2Nlc3NfdG9rZW4=::46b', 'always', 60 %}"},"metaSortKey":-1646673036424.3125,"isPrivate":false,"settingStoreCookies":true,"settingSendCookies":true,"settingDisableRenderRequestBody":false,"settingEncodeUrl":true,"settingRebuildPath":true,"settingFollowRedirects":"global","_type":"request"},{"_id":"fld_e535fc869e1d46c6804962e8fa266144","parentId":"fld_8fa0da45da9343238df5705e0b798b18","modified":1654991170094,"created":1654991167378,"name":"Category","description":"","environment":{},"environmentPropertyOrder":null,"metaSortKey":-1654990664335,"_type":"request_group"},{"_id":"req_99c06ef9213b4bc8b1fb7b32ce2188f8","parentId":"fld_a1438fd0ca7641f0af524f09a8e63ab6","modified":1654982481049,"created":1654982478965,"url":"{{ _.serverUrl }}:{{ _.serverPort }}/dev/author/generate","name":"generate","description":"","method":"POST","body":{"mimeType":"application/json","text":"{\n\t\"number\": 5\n}"},"parameters":[],"headers":[{"name":"Content-Type","value":"application/json","id":"pair_ecaf36ef21c747a9a920cc3500e7df71"}],"authentication":{"type":"bearer","token":"{% response 'body', 'req_ae2a859001a9428ea82d8e044d2d3eb1', 'b64::JC5hY2Nlc3NfdG9rZW4=::46b', 'always', 60 %}"},"metaSortKey":-1646673036416.5,"isPrivate":false,"settingStoreCookies":true,"settingSendCookies":true,"settingDisableRenderRequestBody":false,"settingEncodeUrl":true,"settingRebuildPath":true,"settingFollowRedirects":"global","_type":"request"},{"_id":"fld_a1438fd0ca7641f0af524f09a8e63ab6","parentId":"fld_8fa0da45da9343238df5705e0b798b18","modified":1654991295979,"created":1653858048717,"name":"post","description":"","environment":{},"environmentPropertyOrder":null,"metaSortKey":-1654990664313.125,"_type":"request_group"},{"_id":"req_8bfa4f366dc34cefb5a77061037f62d5","parentId":"fld_ded89240738645cbbe65b96083ed2fb5","modified":1654982486962,"created":1654982485183,"url":"{{ _.serverUrl }}:{{ _.serverPort }}/dev/author/generate","name":"generate","description":"","method":"POST","body":{"mimeType":"application/json","text":"{\n\t\"number\": 5\n}"},"parameters":[],"headers":[{"name":"Content-Type","value":"application/json","id":"pair_ecaf36ef21c747a9a920cc3500e7df71"}],"authentication":{"type":"bearer","token":"{% response 'body', 'req_ae2a859001a9428ea82d8e044d2d3eb1', 'b64::JC5hY2Nlc3NfdG9rZW4=::46b', 'always', 60 %}"},"metaSortKey":-1646673036422.75,"isPrivate":false,"settingStoreCookies":true,"settingSendCookies":true,"settingDisableRenderRequestBody":false,"settingEncodeUrl":true,"settingRebuildPath":true,"settingFollowRedirects":"global","_type":"request"},{"_id":"fld_ded89240738645cbbe65b96083ed2fb5","parentId":"fld_8fa0da45da9343238df5705e0b798b18","modified":1654991304032,"created":1653858035926,"name":"quote","description":"","environment":{},"environmentPropertyOrder":null,"metaSortKey":-1654990664311.5625,"_type":"request_group"},{"_id":"req_111bca1c3cea485e9ffeea7c38e53760","parentId":"fld_97f40d16df3f44e585903f6db4ec2131","modified":1653834171238,"created":1653832465508,"url":"{{ _.serverUrl }}:{{ _.serverPort }}/dev/user/regenerate","name":"regenerate Base Admins","description":"","method":"POST","body":{},"parameters":[],"headers":[],"authentication":{},"metaSortKey":-1653832465508,"isPrivate":false,"settingStoreCookies":true,"settingSendCookies":true,"settingDisableRenderRequestBody":false,"settingEncodeUrl":true,"settingRebuildPath":true,"settingFollowRedirects":"global","_type":"request"},{"_id":"fld_97f40d16df3f44e585903f6db4ec2131","parentId":"fld_8fa0da45da9343238df5705e0b798b18","modified":1653831984163,"created":1653831984163,"name":"user","description":"","environment":{},"environmentPropertyOrder":null,"metaSortKey":-1653831984163,"_type":"request_group"},{"_id":"req_36abbacf6b0d45d0a1e2583e34f9ee56","parentId":"fld_97f40d16df3f44e585903f6db4ec2131","modified":1654978156803,"created":1646676078148,"url":"{{ _.serverUrl }}:{{ _.serverPort }}/dev/user/generate","name":"generate","description":"","method":"POST","body":{"mimeType":"application/json","text":"{\n\t\"number\": 5,\n\t\"type\": \"lambda\"\n}"},"parameters":[],"headers":[{"name":"Content-Type","value":"application/json","id":"pair_ecaf36ef21c747a9a920cc3500e7df71"}],"authentication":{"type":"bearer","token":"{% response 'body', 'req_ae2a859001a9428ea82d8e044d2d3eb1', 'b64::JC5hY2Nlc3NfdG9rZW4=::46b', 'always', 60 %}"},"metaSortKey":-1646673036454,"isPrivate":false,"settingStoreCookies":true,"settingSendCookies":true,"settingDisableRenderRequestBody":false,"settingEncodeUrl":true,"settingRebuildPath":true,"settingFollowRedirects":"global","_type":"request"},{"_id":"req_d91e107e6f3840198e054665e8abae03","parentId":"fld_97f40d16df3f44e585903f6db4ec2131","modified":1654978165723,"created":1646673036404,"url":"{{ _.serverUrl }}:{{ _.serverPort }}/dev/user/flush","name":"flush","description":"","method":"DELETE","body":{},"parameters":[],"headers":[],"authentication":{"type":"bearer","token":"{% response 'body', 'req_ae2a859001a9428ea82d8e044d2d3eb1', 'b64::JC5hY2Nlc3NfdG9rZW4=::46b', 'always', 60 %}"},"metaSortKey":-1646673036404,"isPrivate":false,"settingStoreCookies":true,"settingSendCookies":true,"settingDisableRenderRequestBody":false,"settingEncodeUrl":true,"settingRebuildPath":true,"settingFollowRedirects":"global","_type":"request"},{"_id":"req_7a658e3a82d14e5e9bf60b41c96800f2","parentId":"fld_e8366056e204469ebb5fad23838f163c","modified":1654990862521,"created":1654990831468,"url":"{{ _.serverUrl }}:{{ _.serverPort }}/author/all","name":"Get All","description":"","method":"GET","body":{},"parameters":[],"headers":[],"authentication":{},"metaSortKey":-1654990831468,"isPrivate":false,"settingStoreCookies":true,"settingSendCookies":true,"settingDisableRenderRequestBody":false,"settingEncodeUrl":true,"settingRebuildPath":true,"settingFollowRedirects":"global","_type":"request"},{"_id":"fld_e8366056e204469ebb5fad23838f163c","parentId":"wrk_d5720fa7dd8b432da33f10272aca5071","modified":1654990743883,"created":1653858061664,"name":"Author","description":"","environment":{},"environmentPropertyOrder":null,"metaSortKey":-1650160521348,"_type":"request_group"},{"_id":"req_d2ef0eef19f541f4b9989d709f072d44","parentId":"fld_e8366056e204469ebb5fad23838f163c","modified":1654990943823,"created":1654990893195,"url":"{{ _.serverUrl }}:{{ _.serverPort }}/author/create","name":"Create","description":"","method":"POST","body":{},"parameters":[],"headers":[],"authentication":{"type":"bearer","token":"{% response 'body', 'req_ae2a859001a9428ea82d8e044d2d3eb1', 'b64::JC5hY2Nlc3NfdG9rZW4=::46b', 'always', 60 %}"},"metaSortKey":-1654411648488,"isPrivate":false,"settingStoreCookies":true,"settingSendCookies":true,"settingDisableRenderRequestBody":false,"settingEncodeUrl":true,"settingRebuildPath":true,"settingFollowRedirects":"global","_type":"request"},{"_id":"req_396da64477a24817a3f15b7da5495a24","parentId":"fld_e8366056e204469ebb5fad23838f163c","modified":1654990964443,"created":1654990956358,"url":"{{ _.serverUrl }}:{{ _.serverPort }}/author/delete","name":"Delete","description":"","method":"DELETE","body":{},"parameters":[],"headers":[],"authentication":{"type":"bearer","token":"{% response 'body', 'req_ae2a859001a9428ea82d8e044d2d3eb1', 'b64::JC5hY2Nlc3NfdG9rZW4=::46b', 'always', 60 %}"},"metaSortKey":-1654122056998,"isPrivate":false,"settingStoreCookies":true,"settingSendCookies":true,"settingDisableRenderRequestBody":false,"settingEncodeUrl":true,"settingRebuildPath":true,"settingFollowRedirects":"global","_type":"request"},{"_id":"req_fc9b5767fd9842d08b8c09fab1dce7fa","parentId":"fld_e8366056e204469ebb5fad23838f163c","modified":1654990999439,"created":1654990988566,"url":"{{ _.serverUrl }}:{{ _.serverPort }}/author/from-quote","name":"Get From Quote","description":"","method":"GET","body":{},"parameters":[],"headers":[],"authentication":{"type":"bearer","token":"{% response 'body', 'req_ae2a859001a9428ea82d8e044d2d3eb1', 'b64::JC5hY2Nlc3NfdG9rZW4=::46b', 'always', 60 %}"},"metaSortKey":-1653977261253,"isPrivate":false,"settingStoreCookies":true,"settingSendCookies":true,"settingDisableRenderRequestBody":false,"settingEncodeUrl":true,"settingRebuildPath":true,"settingFollowRedirects":"global","_type":"request"},{"_id":"req_bad459ae26eb4e0c9ad3da6dc376aaec","parentId":"fld_e8366056e204469ebb5fad23838f163c","modified":1654991035931,"created":1654991013295,"url":"{{ _.serverUrl }}:{{ _.serverPort }}/author/from-quote","name":"Get One","description":"","method":"GET","body":{},"parameters":[],"headers":[],"authentication":{"type":"bearer","token":"{% response 'body', 'req_ae2a859001a9428ea82d8e044d2d3eb1', 'b64::JC5hY2Nlc3NfdG9rZW4=::46b', 'always', 60 %}"},"metaSortKey":-1653959161784.875,"isPrivate":false,"settingStoreCookies":true,"settingSendCookies":true,"settingDisableRenderRequestBody":false,"settingEncodeUrl":true,"settingRebuildPath":true,"settingFollowRedirects":"global","_type":"request"},{"_id":"req_ec3ef54eb9c44c4a99686cd7ae6d59c8","parentId":"fld_e8366056e204469ebb5fad23838f163c","modified":1654991105706,"created":1654991025395,"url":"{{ _.serverUrl }}:{{ _.serverPort }}/author/create","name":"Update","description":"","method":"POST","body":{},"parameters":[],"headers":[],"authentication":{"type":"bearer","token":"{% response 'body', 'req_ae2a859001a9428ea82d8e044d2d3eb1', 'b64::JC5hY2Nlc3NfdG9rZW4=::46b', 'always', 60 %}"},"metaSortKey":-1653941062316.75,"isPrivate":false,"settingStoreCookies":true,"settingSendCookies":true,"settingDisableRenderRequestBody":false,"settingEncodeUrl":true,"settingRebuildPath":true,"settingFollowRedirects":"global","_type":"request"},{"_id":"req_d731f08cb6744ba2925859fb18806211","parentId":"fld_cad54fce2e1247859d79dd87d32fe311","modified":1654991132008,"created":1654991124829,"url":"{{ _.serverUrl }}:{{ _.serverPort }}/category/all","name":"Get All","description":"","method":"GET","body":{},"parameters":[],"headers":[],"authentication":{},"metaSortKey":-1654266852793,"isPrivate":false,"settingStoreCookies":true,"settingSendCookies":true,"settingDisableRenderRequestBody":false,"settingEncodeUrl":true,"settingRebuildPath":true,"settingFollowRedirects":"global","_type":"request"},{"_id":"fld_cad54fce2e1247859d79dd87d32fe311","parentId":"wrk_d5720fa7dd8b432da33f10272aca5071","modified":1654990784770,"created":1654990703074,"name":"Category","description":"","environment":{},"environmentPropertyOrder":null,"metaSortKey":-1649242657730.5,"_type":"request_group"},{"_id":"req_c9f736d827f144d5b70dbc6ea55bc90f","parentId":"fld_cad54fce2e1247859d79dd87d32fe311","modified":1654991056974,"created":1654991045885,"url":"{{ _.serverUrl }}:{{ _.serverPort }}/category/create","name":"Create","description":"","method":"POST","body":{},"parameters":[],"headers":[],"authentication":{"type":"bearer","token":"{% response 'body', 'req_ae2a859001a9428ea82d8e044d2d3eb1', 'b64::JC5hY2Nlc3NfdG9rZW4=::46b', 'always', 60 %}"},"metaSortKey":-1654266852743,"isPrivate":false,"settingStoreCookies":true,"settingSendCookies":true,"settingDisableRenderRequestBody":false,"settingEncodeUrl":true,"settingRebuildPath":true,"settingFollowRedirects":"global","_type":"request"},{"_id":"req_e17f359b5e0541c7b05edd9b1358c6a2","parentId":"fld_cad54fce2e1247859d79dd87d32fe311","modified":1654991094558,"created":1654991068944,"url":"{{ _.serverUrl }}:{{ _.serverPort }}/category/delete","name":"Delete","description":"","method":"DELETE","body":{"mimeType":"application/json","text":"{\n\t\"id\": 1\n}"},"parameters":[],"headers":[{"name":"Content-Type","value":"application/json","id":"pair_77ca6476c7834b659a11649c764cb87d"}],"authentication":{"type":"bearer","token":"{% response 'body', 'req_ae2a859001a9428ea82d8e044d2d3eb1', 'b64::JC5hY2Nlc3NfdG9rZW4=::46b', 'always', 60 %}"},"metaSortKey":-1654266852693,"isPrivate":false,"settingStoreCookies":true,"settingSendCookies":true,"settingDisableRenderRequestBody":false,"settingEncodeUrl":true,"settingRebuildPath":true,"settingFollowRedirects":"global","_type":"request"},{"_id":"req_d38b8821bbdb4374a393fc88c723aa31","parentId":"fld_cad54fce2e1247859d79dd87d32fe311","modified":1654991113224,"created":1654991111029,"url":"{{ _.serverUrl }}:{{ _.serverPort }}/author/create","name":"Update","description":"","method":"POST","body":{},"parameters":[],"headers":[],"authentication":{"type":"bearer","token":"{% response 'body', 'req_ae2a859001a9428ea82d8e044d2d3eb1', 'b64::JC5hY2Nlc3NfdG9rZW4=::46b', 'always', 60 %}"},"metaSortKey":-1654266852643,"isPrivate":false,"settingStoreCookies":true,"settingSendCookies":true,"settingDisableRenderRequestBody":false,"settingEncodeUrl":true,"settingRebuildPath":true,"settingFollowRedirects":"global","_type":"request"},{"_id":"req_e8e52a679e4d44768ab658c715f68bdc","parentId":"fld_966f0d1f8b2d4d7eac0d996c21867e4f","modified":1647001361996,"created":1646930614325,"url":"{{ _.serverUrl }}:{{ _.serverPort }}/quote/id/","name":"delete quote by id","description":"","method":"DELETE","body":{"mimeType":"application/json","text":"{\n\t\"id\": \"62295a5760517fa9ccb97b2d\"\n}"},"parameters":[],"headers":[{"name":"Content-Type","value":"application/json","id":"pair_c87e7013437d429d80bed44c966edca4"}],"authentication":{"type":"bearer","token":"{% response 'body', 'req_ae2a859001a9428ea82d8e044d2d3eb1', 'b64::JC5hY2Nlc3NfdG9rZW4=::46b', 'always', 60 %}"},"metaSortKey":-1646930614325,"isPrivate":false,"settingStoreCookies":true,"settingSendCookies":true,"settingDisableRenderRequestBody":false,"settingEncodeUrl":true,"settingRebuildPath":true,"settingFollowRedirects":"global","_type":"request"},{"_id":"fld_966f0d1f8b2d4d7eac0d996c21867e4f","parentId":"wrk_d5720fa7dd8b432da33f10272aca5071","modified":1654990816266,"created":1646489066828,"name":"Quote","description":"","environment":{},"environmentPropertyOrder":null,"metaSortKey":-1648382160589.0938,"_type":"request_group"},{"_id":"req_8ec36f042d1f4ea0b54f6f2d2d837227","parentId":"fld_966f0d1f8b2d4d7eac0d996c21867e4f","modified":1646867787895,"created":1646501007118,"url":"{{ _.serverUrl }}:{{ _.serverPort }}/quote/all","name":"get all quotes","description":"","method":"GET","body":{},"parameters":[],"headers":[],"authentication":{},"metaSortKey":-1646501007118,"isPrivate":false,"settingStoreCookies":true,"settingSendCookies":true,"settingDisableRenderRequestBody":false,"settingEncodeUrl":true,"settingRebuildPath":true,"settingFollowRedirects":"global","_type":"request"},{"_id":"req_03af0a058d2142e99cd66640b31575bb","parentId":"fld_966f0d1f8b2d4d7eac0d996c21867e4f","modified":1647084993035,"created":1646500993869,"url":"{{ _.serverUrl }}:{{ _.serverPort }}/quote/random-js","name":"get random Quote","description":"","method":"GET","body":{},"parameters":[],"headers":[],"authentication":{},"metaSortKey":-1646501003805.75,"isPrivate":false,"settingStoreCookies":true,"settingSendCookies":true,"settingDisableRenderRequestBody":false,"settingEncodeUrl":true,"settingRebuildPath":true,"settingFollowRedirects":"global","_type":"request"},{"_id":"req_285af99613ce462a80382a2e2c237c7a","parentId":"fld_966f0d1f8b2d4d7eac0d996c21867e4f","modified":1647008082504,"created":1646501049812,"url":"{{ _.serverUrl }}:{{ _.serverPort }}/quote/generate","name":"Generate quotes","description":"","method":"POST","body":{"mimeType":"application/json","text":"{\n\t\"numberOfQuotes\": 150\n}"},"parameters":[],"headers":[{"name":"Content-Type","value":"application/json","id":"pair_58949ad561164b6aaf8dfdbcb26d060a"}],"authentication":{"type":"bearer","token":"{% response 'body', 'req_ae2a859001a9428ea82d8e044d2d3eb1', 'b64::JC5hY2Nlc3NfdG9rZW4=::46b', 'always', 60 %}"},"metaSortKey":-1646501002149.625,"isPrivate":false,"settingStoreCookies":true,"settingSendCookies":true,"settingDisableRenderRequestBody":false,"settingEncodeUrl":true,"settingRebuildPath":true,"settingFollowRedirects":"global","_type":"request"},{"_id":"req_491813d0606140d78b57c18bc093f483","parentId":"fld_966f0d1f8b2d4d7eac0d996c21867e4f","modified":1646874672745,"created":1646501021825,"url":"{{ _.serverUrl }}:{{ _.serverPort }}/quote/create-one","name":"Create quote","description":"","method":"POST","body":{"mimeType":"application/json","text":"{\n\t\"author\": \"bibou\",\n\t\"text\": \"bibou va a sdf la plage\"\n}"},"parameters":[],"headers":[{"name":"Content-Type","value":"application/json","id":"pair_47e009f308094fa5a8a7685fc70d4495"}],"authentication":{"type":"bearer","token":"{% response 'body', 'req_ae2a859001a9428ea82d8e044d2d3eb1', 'b64::JC5hY2Nlc3NfdG9rZW4=::46b', 'always', 60 %}"},"metaSortKey":-1646501000493.5,"isPrivate":false,"settingStoreCookies":true,"settingSendCookies":true,"settingDisableRenderRequestBody":false,"settingEncodeUrl":true,"settingRebuildPath":true,"settingFollowRedirects":"global","_type":"request"},{"_id":"req_cf88ef504e894459b91e52ca7eaad2a3","parentId":"fld_966f0d1f8b2d4d7eac0d996c21867e4f","modified":1646876677763,"created":1646664952966,"url":"{{ _.serverUrl }}:{{ _.serverPort }}/quote/flush","name":"flush","description":"","method":"DELETE","body":{},"parameters":[],"headers":[],"authentication":{"type":"bearer","token":"{% response 'body', 'req_ae2a859001a9428ea82d8e044d2d3eb1', 'b64::JC5hY2Nlc3NfdG9rZW4=::46b', 'always', 60 %}"},"metaSortKey":-1646501000443.5,"isPrivate":false,"settingStoreCookies":true,"settingSendCookies":true,"settingDisableRenderRequestBody":false,"settingEncodeUrl":true,"settingRebuildPath":true,"settingFollowRedirects":"global","_type":"request"},{"_id":"req_2e3051af756f410783f8dd680f1d079a","parentId":"fld_24485ba5d9524086a807867becce013c","modified":1654978173757,"created":1646705156625,"url":"{{ _.serverUrl }}:{{ _.serverPort }}/user/count","name":"usercount","description":"","method":"GET","body":{},"parameters":[],"headers":[],"authentication":{"type":"bearer","token":"{% response 'body', 'req_ae2a859001a9428ea82d8e044d2d3eb1', 'b64::JC5hY2Nlc3NfdG9rZW4=::46b', 'always', 60 %}"},"metaSortKey":-1646674557276,"isPrivate":false,"settingStoreCookies":true,"settingSendCookies":true,"settingDisableRenderRequestBody":false,"settingEncodeUrl":true,"settingRebuildPath":true,"settingFollowRedirects":"global","_type":"request"},{"_id":"fld_24485ba5d9524086a807867becce013c","parentId":"wrk_d5720fa7dd8b432da33f10272aca5071","modified":1646665062223,"created":1646489059630,"name":"User","description":"","environment":{},"environmentPropertyOrder":null,"metaSortKey":-1646489066878,"_type":"request_group"},{"_id":"req_09de07fc8972495b852f3cd4ba27cf31","parentId":"fld_24485ba5d9524086a807867becce013c","modified":1653858078193,"created":1646743813326,"url":"{{ _.serverUrl }}:{{ _.serverPort }}/user/delete","name":"delete user","description":"","method":"DELETE","body":{"mimeType":"application/json","text":"{\n\t\"email\": \"bob@bob.bob\"\n}"},"parameters":[],"headers":[{"name":"Content-Type","value":"application/json","id":"pair_ae998dcf6cf04c5b8631c85ba8f0eeb9"}],"authentication":{"type":"bearer","token":"{% response 'body', 'req_ae2a859001a9428ea82d8e044d2d3eb1', 'b64::JC5hY2Nlc3NfdG9rZW4=::46b', 'always', 60 %}"},"metaSortKey":-1646672474710,"isPrivate":false,"settingStoreCookies":true,"settingSendCookies":true,"settingDisableRenderRequestBody":false,"settingEncodeUrl":true,"settingRebuildPath":true,"settingFollowRedirects":"global","_type":"request"},{"_id":"req_ae2a859001a9428ea82d8e044d2d3eb1","parentId":"fld_24485ba5d9524086a807867becce013c","modified":1654975906288,"created":1646490163072,"url":"{{ _.serverUrl }}:{{ _.serverPort }}/user/login","name":"Login","description":"","method":"POST","body":{"mimeType":"application/x-www-form-urlencoded","params":[{"id":"pair_7447848446fd406898bfc329eb7be5b2","name":"email","value":"bobby@bobby.bob","description":"","disabled":false},{"id":"pair_644181221cc24e199fd0787e505e327c","name":"password","value":"bobby555666","description":""},{"id":"pair_aef05e5f23f84c69a36c3d8004af5fbc","name":"email","value":"bobby@bobby.bub","description":"","disabled":true}]},"parameters":[],"headers":[{"name":"Content-Type","value":"application/x-www-form-urlencoded","id":"pair_bcf1648f69204cbd8d6720f4bc38c521"}],"authentication":{},"metaSortKey":-1646490163072,"isPrivate":false,"settingStoreCookies":true,"settingSendCookies":true,"settingDisableRenderRequestBody":false,"settingEncodeUrl":true,"settingRebuildPath":true,"settingFollowRedirects":"global","_type":"request"},{"_id":"req_4000d010b0e74f20b46dac4a7b1cd744","parentId":"fld_24485ba5d9524086a807867becce013c","modified":1654978198748,"created":1648894333102,"url":"{{ _.serverUrl }}:{{ _.serverPort }}/user/login","name":"Wrong Login","description":"","method":"POST","body":{"mimeType":"application/x-www-form-urlencoded","params":[{"id":"pair_7447848446fd406898bfc329eb7be5b2","name":"email","value":"bobby@bobby.bob","description":""},{"id":"pair_644181221cc24e199fd0787e505e327c","name":"password","value":"bobby55fdg","description":""}]},"parameters":[],"headers":[{"name":"Content-Type","value":"application/x-www-form-urlencoded","id":"pair_bcf1648f69204cbd8d6720f4bc38c521"}],"authentication":{},"metaSortKey":-1646489620577,"isPrivate":false,"settingStoreCookies":true,"settingSendCookies":true,"settingDisableRenderRequestBody":false,"settingEncodeUrl":true,"settingRebuildPath":true,"settingFollowRedirects":"global","_type":"request"},{"_id":"req_561cd9bbc92548dfbe73cedbb68425ce","parentId":"fld_24485ba5d9524086a807867becce013c","modified":1654975950224,"created":1646489078082,"url":"{{ _.serverUrl }}:{{ _.serverPort }}/user/register","name":"Register","description":"","method":"POST","body":{"mimeType":"application/x-www-form-urlencoded","params":[{"id":"pair_8606837165b840d7ac8c827d625db857","name":"email","value":"bobby@bobby.bib","description":""},{"id":"pair_4ae06f07e3ab4e90982ed2fb8b142f14","name":"password","value":"bobby555666","description":""}]},"parameters":[],"headers":[{"name":"Content-Type","value":"application/x-www-form-urlencoded","id":"pair_29eee2e1514242e5b2d8f5ce5e0be856"}],"authentication":{},"metaSortKey":-1646489078082,"isPrivate":false,"settingStoreCookies":true,"settingSendCookies":true,"settingDisableRenderRequestBody":false,"settingEncodeUrl":true,"settingRebuildPath":true,"settingFollowRedirects":"global","_type":"request"},{"_id":"env_315ae997498d2f48756c856a35aa287ce7de226a","parentId":"wrk_d5720fa7dd8b432da33f10272aca5071","modified":1646488851265,"created":1646488846151,"name":"Base Environment","data":{},"dataPropertyOrder":{},"color":null,"isPrivate":false,"metaSortKey":1646488846151,"_type":"environment"},{"_id":"jar_315ae997498d2f48756c856a35aa287ce7de226a","parentId":"wrk_d5720fa7dd8b432da33f10272aca5071","modified":1646488846153,"created":1646488846153,"name":"Default Jar","cookies":[],"_type":"cookie_jar"},{"_id":"spc_1108dca0a85b47dcb7b610988a8e1699","parentId":"wrk_d5720fa7dd8b432da33f10272aca5071","modified":1646488846141,"created":1646488846141,"fileName":"Beta","contents":"","contentType":"yaml","_type":"api_spec"},{"_id":"env_c00e8bd6670b4d8f9a1b8443c8906224","parentId":"env_315ae997498d2f48756c856a35aa287ce7de226a","modified":1646705793673,"created":1646488855294,"name":"Dev","data":{"serverUrl":"http://localhost","serverPort":"3000","user":{"password":"","email":"","accessToken":""}},"dataPropertyOrder":{"&":["serverUrl","serverPort","user"],"&~|user":["password","email","accessToken"]},"color":null,"isPrivate":false,"metaSortKey":1646488855294,"_type":"environment"},{"_id":"env_4ddb88c83b314bee9f6c89696a691481","parentId":"env_315ae997498d2f48756c856a35aa287ce7de226a","modified":1646488935467,"created":1646488865389,"name":"Prod","data":{"serverUrl":"","serverPort":""},"dataPropertyOrder":{"&":["serverUrl","serverPort"]},"color":null,"isPrivate":false,"metaSortKey":1646488865389,"_type":"environment"}]}